django_abc/__init__.py
django_abc-1.0.0.dist-info/DESCRIPTION.rst
django_abc-1.0.0.dist-info/METADATA
django_abc-1.0.0.dist-info/RECORD
django_abc-1.0.0.dist-info/WHEEL
django_abc-1.0.0.dist-info/metadata.json
django_abc-1.0.0.dist-info/top_level.txt
